pypibatch/__init__.py
pypibatch/__version__.py
pypibatch/main.py
pypibatch/py.typed
pypibatch-0.2.2.dist-info/LICENSE
pypibatch-0.2.2.dist-info/METADATA
pypibatch-0.2.2.dist-info/WHEEL
pypibatch-0.2.2.dist-info/top_level.txt
pypibatch-0.2.2.dist-info/RECORD
