Metadata-Version: 2.1
Name: pypibatch
Version: 0.2.2
Summary: A simple OSI PI Batch client for python
Home-page: https://github.com/newvicx/pypibatch
Author: Chris Newville
Author-email: chrisnewville1396@gmail.com
License: MIT
Project-URL: Changelog, https://github.com/newvicx/pypibatch/blob/master/CHANGELOG.md
Project-URL: Source, https://github.com/newvicx/pypibatch
Classifier: Development Status :: 4 - Beta
Classifier: Environment :: Web Environment
Classifier: Intended Audience :: Developers
Classifier: License :: OSI Approved :: MIT License
Classifier: Operating System :: Microsoft :: Windows
Classifier: Topic :: Internet :: WWW/HTTP
Classifier: Framework :: AsyncIO
Classifier: Programming Language :: Python :: 3
Classifier: Programming Language :: Python :: 3 :: Only
Requires-Python: >=3.6
License-File: LICENSE
Requires-Dist: pandas (>=1.0)
